[
  {
    "file": "basic.ml",
    "title": "Alpha: node initialization (full mode)",
    "tags": [
      "alpha",
      "basic",
      "node",
      "full"
    ],
    "successful_runs": {
      "total_time": "9343863",
      "count": "1"
    },
    "failed_runs": {
      "total_time": "0",
      "count": "0"
    }
  },
  {
    "file": "client_config.ml",
    "title": "Alpha: additional bootstrap accounts",
    "tags": [
      "alpha",
      "client",
      "bootstrap",
      "accounts"
    ],
    "successful_runs": {
      "total_time": "7888715",
      "count": "1"
    },
    "failed_runs": {
      "total_time": "0",
      "count": "0"
    }
  },
  {
    "file": "bootstrap.ml",
    "title": "Alpha: node synchronization (archive / rolling)",
    "tags": [
      "alpha",
      "bootstrap",
      "node",
      "sync",
      "activate",
      "bake",
      "primary_archive",
      "secondary_rolling"
    ],
    "successful_runs": {
      "total_time": "21438105",
      "count": "1"
    },
    "failed_runs": {
      "total_time": "0",
      "count": "0"
    }
  },
  {
    "file": "mockup.ml",
    "title": "Hangzhou: (Mockup) Transfer (asynchronous)",
    "tags": [
      "hangzhou",
      "mockup",
      "client",
      "transfer",
      "asynchronous"
    ],
    "successful_runs": {
      "total_time": "1874916",
      "count": "1"
    },
    "failed_runs": {
      "total_time": "0",
      "count": "0"
    }
  },
  {
    "file": "mockup.ml",
    "title": "Ithaca: (Mockup) Transfer (asynchronous)",
    "tags": [
      "ithaca",
      "mockup",
      "client",
      "transfer",
      "asynchronous"
    ],
    "successful_runs": {
      "total_time": "1255397",
      "count": "1"
    },
    "failed_runs": {
      "total_time": "0",
      "count": "0"
    }
  },
  {
    "file": "mockup.ml",
    "title": "Alpha: (Mockup) multiple transfer simulation",
    "tags": [
      "alpha",
      "mockup",
      "client",
      "multiple",
      "transfer"
    ],
    "successful_runs": {
      "total_time": "1065402",
      "count": "1"
    },
    "failed_runs": {
      "total_time": "0",
      "count": "0"
    }
  },
  {
    "file": "node_event_level.ml",
    "title": "Alpha: event level debug",
    "tags": [
      "alpha",
      "node",
      "event"
    ],
    "successful_runs": {
      "total_time": "24063591",
      "count": "1"
    },
    "failed_runs": {
      "total_time": "0",
      "count": "0"
    }
  },
  {
    "file": "proxy.ml",
    "title": "Hangzhou: (Proxy) Transfer",
    "tags": [
      "hangzhou",
      "proxy",
      "transfer"
    ],
    "successful_runs": {
      "total_time": "7588037",
      "count": "1"
    },
    "failed_runs": {
      "total_time": "0",
      "count": "0"
    }
  },
  {
    "file": "proxy.ml",
    "title": "Alpha: (Proxy) (/chains/main/blocks/head/helpers/baking_rights?all=true) No useless RPC call",
    "tags": [
      "alpha",
      "proxy",
      "rpc",
      "get"
    ],
    "successful_runs": {
      "total_time": "5944017",
      "count": "1"
    },
    "failed_runs": {
      "total_time": "0",
      "count": "0"
    }
  },
  {
    "file": "proxy.ml",
    "title": "Ithaca: (Proxy) (/chains/main/blocks/head/context/delegates) No useless RPC call",
    "tags": [
      "ithaca",
      "proxy",
      "rpc",
      "get"
    ],
    "successful_runs": {
      "total_time": "5908504",
      "count": "1"
    },
    "failed_runs": {
      "total_time": "0",
      "count": "0"
    }
  },
  {
    "file": "proxy.ml",
    "title": "Ithaca: (Proxy) (/chains/main/blocks/head/helpers/endorsing_rights) No useless RPC call",
    "tags": [
      "ithaca",
      "proxy",
      "rpc",
      "get"
    ],
    "successful_runs": {
      "total_time": "5899760",
      "count": "1"
    },
    "failed_runs": {
      "total_time": "0",
      "count": "0"
    }
  },
  {
    "file": "proxy.ml",
    "title": "Ithaca: (Proxy) (/chains/main/blocks/head/votes/current_proposal) No useless RPC call",
    "tags": [
      "ithaca",
      "proxy",
      "rpc",
      "get"
    ],
    "successful_runs": {
      "total_time": "5907575",
      "count": "1"
    },
    "failed_runs": {
      "total_time": "0",
      "count": "0"
    }
  },
  {
    "file": "proxy.ml",
    "title": "Hangzhou: (Proxy) (/chains/main/blocks/head/helpers/baking_rights) No useless RPC call",
    "tags": [
      "hangzhou",
      "proxy",
      "rpc",
      "get"
    ],
    "successful_runs": {
      "total_time": "6131928",
      "count": "1"
    },
    "failed_runs": {
      "total_time": "0",
      "count": "0"
    }
  },
  {
    "file": "proxy.ml",
    "title": "Hangzhou: (Proxy) (/chains/main/blocks/head/votes/current_quorum) No useless RPC call",
    "tags": [
      "hangzhou",
      "proxy",
      "rpc",
      "get"
    ],
    "successful_runs": {
      "total_time": "6018187",
      "count": "1"
    },
    "failed_runs": {
      "total_time": "0",
      "count": "0"
    }
  },
  {
    "file": "proxy.ml",
    "title": "Alpha: (Proxy) (/chains/main/blocks/head/helpers/baking_rights) Cache at most once",
    "tags": [
      "alpha",
      "proxy",
      "rpc",
      "get"
    ],
    "successful_runs": {
      "total_time": "5784733",
      "count": "1"
    },
    "failed_runs": {
      "total_time": "0",
      "count": "0"
    }
  },
  {
    "file": "proxy.ml",
    "title": "Hangzhou: (Proxy) (/chains/main/blocks/head/helpers/current_level) Cache at most once",
    "tags": [
      "hangzhou",
      "proxy",
      "rpc",
      "get"
    ],
    "successful_runs": {
      "total_time": "5973069",
      "count": "1"
    },
    "failed_runs": {
      "total_time": "0",
      "count": "0"
    }
  },
  {
    "file": "proxy.ml",
    "title": "Hangzhou: (Proxy) (/chains/main/blocks/head/helpers/levels_in_current_cycle) Cache at most once",
    "tags": [
      "hangzhou",
      "proxy",
      "rpc",
      "get"
    ],
    "successful_runs": {
      "total_time": "6124871",
      "count": "1"
    },
    "failed_runs": {
      "total_time": "0",
      "count": "0"
    }
  },
  {
    "file": "proxy.ml",
    "title": "Ithaca: (Proxy) (/chains/main/blocks/head/votes/total_voting_power) Cache at most once",
    "tags": [
      "ithaca",
      "proxy",
      "rpc",
      "get"
    ],
    "successful_runs": {
      "total_time": "5954545",
      "count": "1"
    },
    "failed_runs": {
      "total_time": "0",
      "count": "0"
    }
  },
  {
    "file": "proxy.ml",
    "title": "Alpha: (Proxy) RPC get's location",
    "tags": [
      "alpha",
      "proxy",
      "location",
      "rpc",
      "get"
    ],
    "successful_runs": {
      "total_time": "6760050",
      "count": "1"
    },
    "failed_runs": {
      "total_time": "0",
      "count": "0"
    }
  },
  {
    "file": "proxy.ml",
    "title": "Alpha: (Proxy) split_key heuristic",
    "tags": [
      "alpha",
      "proxy",
      "rpc",
      "get"
    ],
    "successful_runs": {
      "total_time": "11571491",
      "count": "1"
    },
    "failed_runs": {
      "total_time": "0",
      "count": "0"
    }
  },
  {
    "file": "p2p.ml",
    "title": "Alpha: check peer option",
    "tags": [
      "alpha",
      "p2p",
      "cli",
      "peer"
    ],
    "successful_runs": {
      "total_time": "7170392",
      "count": "1"
    },
    "failed_runs": {
      "total_time": "0",
      "count": "0"
    }
  },
  {
    "file": "protocol_migration.ml",
    "title": "protocol migration at level 15",
    "tags": [
      "protocol",
      "migration",
      "sandbox"
    ],
    "successful_runs": {
      "total_time": "8018246",
      "count": "1"
    },
    "failed_runs": {
      "total_time": "0",
      "count": "0"
    }
  },
  {
    "file": "cache_cache.ml",
    "title": "Alpha: cache cache",
    "tags": [
      "alpha",
      "cache",
      "node",
      "baker"
    ],
    "successful_runs": {
      "total_time": "10804277",
      "count": "1"
    },
    "failed_runs": {
      "total_time": "0",
      "count": "0"
    }
  },
  {
    "file": "mempool.ml",
    "title": "Alpha: Flush mempool",
    "tags": [
      "alpha",
      "mempool",
      "flush"
    ],
    "successful_runs": {
      "total_time": "21830487",
      "count": "1"
    },
    "failed_runs": {
      "total_time": "0",
      "count": "0"
    }
  },
  {
    "file": "mempool.ml",
    "title": "Alpha: Manager_restriction_disable_precheck",
    "tags": [
      "alpha",
      "mempool",
      "manager_restriction",
      "disable_precheck"
    ],
    "successful_runs": {
      "total_time": "11022500",
      "count": "1"
    },
    "failed_runs": {
      "total_time": "0",
      "count": "0"
    }
  },
  {
    "file": "mempool.ml",
    "title": "Ithaca: Manager_restriction_flush_on_ban",
    "tags": [
      "ithaca",
      "mempool",
      "manager_restriction",
      "flush",
      "ban"
    ],
    "successful_runs": {
      "total_time": "11761281",
      "count": "1"
    },
    "failed_runs": {
      "total_time": "0",
      "count": "0"
    }
  },
  {
    "file": "mempool.ml",
    "title": "Alpha: mempool unban operation and reinject",
    "tags": [
      "alpha",
      "mempool",
      "node",
      "ban",
      "reinject"
    ],
    "successful_runs": {
      "total_time": "25110552",
      "count": "1"
    },
    "failed_runs": {
      "total_time": "0",
      "count": "0"
    }
  },
  {
    "file": "mempool.ml",
    "title": "Ithaca: Test prefiltered limits of mempool",
    "tags": [
      "ithaca",
      "mempool",
      "gc",
      "limit"
    ],
    "successful_runs": {
      "total_time": "17868975",
      "count": "1"
    },
    "failed_runs": {
      "total_time": "0",
      "count": "0"
    }
  },
  {
    "file": "mempool.ml",
    "title": "Alpha: Ensure that future endorsement are propagated",
    "tags": [
      "alpha",
      "endorsement",
      "mempool",
      "branch_delayed"
    ],
    "successful_runs": {
      "total_time": "16367090",
      "count": "1"
    },
    "failed_runs": {
      "total_time": "0",
      "count": "0"
    }
  },
  {
    "file": "mempool.ml",
    "title": "Ithaca: Forge pre-filtered operation and check mempool",
    "tags": [
      "ithaca",
      "forge",
      "mempool",
      "pre_filtered"
    ],
    "successful_runs": {
      "total_time": "8458698",
      "count": "1"
    },
    "failed_runs": {
      "total_time": "0",
      "count": "0"
    }
  },
  {
    "file": "mempool.ml",
    "title": "Ithaca: pending operation version",
    "tags": [
      "ithaca",
      "mempool",
      "pending_operations",
      "version"
    ],
    "successful_runs": {
      "total_time": "7875530",
      "count": "1"
    },
    "failed_runs": {
      "total_time": "0",
      "count": "0"
    }
  },
  {
    "file": "mempool.ml",
    "title": "Ithaca: force invalid operation injection",
    "tags": [
      "ithaca",
      "force",
      "mempool"
    ],
    "successful_runs": {
      "total_time": "9893502",
      "count": "1"
    },
    "failed_runs": {
      "total_time": "0",
      "count": "0"
    }
  },
  {
    "file": "mempool.ml",
    "title": "Alpha: mempool filter arrival",
    "tags": [
      "alpha",
      "mempool",
      "node",
      "filter",
      "refused",
      "applied"
    ],
    "successful_runs": {
      "total_time": "12551298",
      "count": "1"
    },
    "failed_runs": {
      "total_time": "0",
      "count": "0"
    }
  },
  {
    "file": "encoding.ml",
    "title": "Hangzhou: encoding regression test: delegate.frozen_balance",
    "tags": [
      "regression",
      "hangzhou",
      "encoding"
    ],
    "successful_runs": {
      "total_time": "663780",
      "count": "1"
    },
    "failed_runs": {
      "total_time": "0",
      "count": "0"
    }
  },
  {
    "file": "encoding.ml",
    "title": "Alpha: encoding regression test: gas",
    "tags": [
      "regression",
      "alpha",
      "encoding"
    ],
    "successful_runs": {
      "total_time": "1959917",
      "count": "1"
    },
    "failed_runs": {
      "total_time": "0",
      "count": "0"
    }
  },
  {
    "file": "encoding.ml",
    "title": "Ithaca: encoding regression test: gas",
    "tags": [
      "regression",
      "ithaca",
      "encoding"
    ],
    "successful_runs": {
      "total_time": "1981339",
      "count": "1"
    },
    "failed_runs": {
      "total_time": "0",
      "count": "0"
    }
  },
  {
    "file": "encoding.ml",
    "title": "Hangzhou: encoding regression test: operation.raw",
    "tags": [
      "regression",
      "hangzhou",
      "encoding"
    ],
    "successful_runs": {
      "total_time": "666104",
      "count": "1"
    },
    "failed_runs": {
      "total_time": "0",
      "count": "0"
    }
  },
  {
    "file": "encoding.ml",
    "title": "Alpha: encoding regression test: raw_level",
    "tags": [
      "regression",
      "alpha",
      "encoding"
    ],
    "successful_runs": {
      "total_time": "1344200",
      "count": "1"
    },
    "failed_runs": {
      "total_time": "0",
      "count": "0"
    }
  },
  {
    "file": "encoding.ml",
    "title": "Ithaca: encoding regression test: raw_level",
    "tags": [
      "regression",
      "ithaca",
      "encoding"
    ],
    "successful_runs": {
      "total_time": "1335953",
      "count": "1"
    },
    "failed_runs": {
      "total_time": "0",
      "count": "0"
    }
  },
  {
    "file": "encoding.ml",
    "title": "Hangzhou: encoding regression test: vote.ballots",
    "tags": [
      "regression",
      "hangzhou",
      "encoding"
    ],
    "successful_runs": {
      "total_time": "678411",
      "count": "1"
    },
    "failed_runs": {
      "total_time": "0",
      "count": "0"
    }
  },
  {
    "file": "proxy.ml",
    "title": "light supports alpha and at least 3 immutable protocols",
    "tags": [
      "client",
      "light",
      "list",
      "protocols"
    ],
    "successful_runs": {
      "total_time": "411590",
      "count": "1"
    },
    "failed_runs": {
      "total_time": "0",
      "count": "0"
    }
  },
  {
    "file": "RPC_test.ml",
    "title": "Alpha: (mode client) RPC regression tests: contracts",
    "tags": [
      "regression",
      "alpha",
      "rpc",
      "contracts"
    ],
    "successful_runs": {
      "total_time": "28508214",
      "count": "1"
    },
    "failed_runs": {
      "total_time": "0",
      "count": "0"
    }
  },
  {
    "file": "RPC_test.ml",
    "title": "Hangzhou: (mode client) RPC regression tests: mempool",
    "tags": [
      "regression",
      "hangzhou",
      "rpc",
      "mempool"
    ],
    "successful_runs": {
      "total_time": "26713315",
      "count": "1"
    },
    "failed_runs": {
      "total_time": "0",
      "count": "0"
    }
  },
  {
    "file": "RPC_test.ml",
    "title": "Alpha: (mode light) RPC regression tests: tx_rollup",
    "tags": [
      "regression",
      "alpha",
      "rpc",
      "tx_rollup"
    ],
    "successful_runs": {
      "total_time": "6901440",
      "count": "1"
    },
    "failed_runs": {
      "total_time": "0",
      "count": "0"
    }
  },
  {
    "file": "RPC_test.ml",
    "title": "Hangzhou: (mode proxy) RPC regression tests: mempool",
    "tags": [
      "regression",
      "hangzhou",
      "rpc",
      "mempool"
    ],
    "successful_runs": {
      "total_time": "26493705",
      "count": "1"
    },
    "failed_runs": {
      "total_time": "0",
      "count": "0"
    }
  },
  {
    "file": "RPC_test.ml",
    "title": "Alpha: (mode proxy_server) RPC regression tests: delegates",
    "tags": [
      "regression",
      "alpha",
      "rpc",
      "delegates"
    ],
    "successful_runs": {
      "total_time": "13627859",
      "count": "1"
    },
    "failed_runs": {
      "total_time": "0",
      "count": "0"
    }
  },
  {
    "file": "RPC_test.ml",
    "title": "Test RPC whitelist @ localhost",
    "tags": [
      "rpc",
      "acl"
    ],
    "successful_runs": {
      "total_time": "4605983",
      "count": "1"
    },
    "failed_runs": {
      "total_time": "0",
      "count": "0"
    }
  },
  {
    "file": "RPC_test.ml",
    "title": "Test RPC no_service_at_valid_prefix @ localhost",
    "tags": [
      "rpc"
    ],
    "successful_runs": {
      "total_time": "4223433",
      "count": "1"
    },
    "failed_runs": {
      "total_time": "0",
      "count": "0"
    }
  },
  {
    "file": "manager_operations.ml",
    "title": "Ithaca: Contract's body illtyped 1",
    "tags": [
      "ithaca",
      "precheck",
      "illtyped",
      "origination",
      "typing"
    ],
    "successful_runs": {
      "total_time": "29389936",
      "count": "1"
    },
    "failed_runs": {
      "total_time": "0",
      "count": "0"
    }
  },
  {
    "file": "manager_operations.ml",
    "title": "Hangzhou: Simple revelation with something that is not a public key",
    "tags": [
      "hangzhou",
      "reveal",
      "revelation"
    ],
    "successful_runs": {
      "total_time": "21031456",
      "count": "1"
    },
    "failed_runs": {
      "total_time": "0",
      "count": "0"
    }
  },
  {
    "file": "manager_operations.ml",
    "title": "Alpha: Correct public key revealed twice in a batch",
    "tags": [
      "alpha",
      "reveal",
      "revelation",
      "batch"
    ],
    "successful_runs": {
      "total_time": "38115167",
      "count": "1"
    },
    "failed_runs": {
      "total_time": "0",
      "count": "0"
    }
  },
  {
    "file": "manager_operations.ml",
    "title": "Ithaca: Two reveals in a batch. Second key is wrong",
    "tags": [
      "ithaca",
      "reveal",
      "revelation"
    ],
    "successful_runs": {
      "total_time": "22781244",
      "count": "1"
    },
    "failed_runs": {
      "total_time": "0",
      "count": "0"
    }
  },
  {
    "file": "manager_operations.ml",
    "title": "Ithaca: Simple transfer not enough balance to pay fees",
    "tags": [
      "ithaca",
      "transaction",
      "transfer"
    ],
    "successful_runs": {
      "total_time": "20510862",
      "count": "1"
    },
    "failed_runs": {
      "total_time": "0",
      "count": "0"
    }
  },
  {
    "file": "manager_operations.ml",
    "title": "Alpha: Simple transfer not enough balance to make transfer",
    "tags": [
      "alpha",
      "transaction",
      "transfer"
    ],
    "successful_runs": {
      "total_time": "31071467",
      "count": "1"
    },
    "failed_runs": {
      "total_time": "0",
      "count": "0"
    }
  },
  {
    "file": "manager_operations.ml",
    "title": "Hangzhou: Simple transfer counter in the future",
    "tags": [
      "hangzhou",
      "transaction",
      "transfer"
    ],
    "successful_runs": {
      "total_time": "62397282",
      "count": "1"
    },
    "failed_runs": {
      "total_time": "0",
      "count": "0"
    }
  },
  {
    "file": "manager_operations.ml",
    "title": "Hangzhou: Test simple transfer with low balance to pay allocation (2)",
    "tags": [
      "hangzhou",
      "transaction",
      "transfer"
    ],
    "successful_runs": {
      "total_time": "49639191",
      "count": "1"
    },
    "failed_runs": {
      "total_time": "0",
      "count": "0"
    }
  },
  {
    "file": "manager_operations.ml",
    "title": "Alpha: Test batch with wrong counters (+1, +2, +2)",
    "tags": [
      "alpha",
      "transaction",
      "transfer",
      "counters",
      "batch"
    ],
    "successful_runs": {
      "total_time": "58431248",
      "count": "1"
    },
    "failed_runs": {
      "total_time": "0",
      "count": "0"
    }
  },
  {
    "file": "replace_by_fees.ml",
    "title": "Ithaca: Second op's fees are equal to replacement fees threshold",
    "tags": [
      "ithaca",
      "replace",
      "fee",
      "manager"
    ],
    "successful_runs": {
      "total_time": "12537401",
      "count": "1"
    },
    "failed_runs": {
      "total_time": "0",
      "count": "0"
    }
  },
  {
    "file": "replace_by_fees.ml",
    "title": "Ithaca: Op2's gas/fee is more important, but fees are not higher than max",
    "tags": [
      "ithaca",
      "replace",
      "fee",
      "manager"
    ],
    "successful_runs": {
      "total_time": "12043697",
      "count": "1"
    },
    "failed_runs": {
      "total_time": "0",
      "count": "0"
    }
  },
  {
    "file": "replace_by_fees.ml",
    "title": "Alpha: Low balance - second op's fees are equal to max_int64-1",
    "tags": [
      "alpha",
      "replace",
      "fee",
      "manager"
    ],
    "successful_runs": {
      "total_time": "16995119",
      "count": "1"
    },
    "failed_runs": {
      "total_time": "0",
      "count": "0"
    }
  },
  {
    "file": "sc_rollup.ml",
    "title": "Alpha: getting a smart-contract rollup address through the client",
    "tags": [
      "regression",
      "alpha",
      "sc_rollup",
      "run",
      "client"
    ],
    "successful_runs": {
      "total_time": "6509330",
      "count": "1"
    },
    "failed_runs": {
      "total_time": "0",
      "count": "0"
    }
  },
  {
    "file": "runtime_script_failure.ml",
    "title": "Alpha: Runtime Script Failure: client force",
    "tags": [
      "alpha",
      "runtime_script_failure"
    ],
    "successful_runs": {
      "total_time": "24422277",
      "count": "1"
    },
    "failed_runs": {
      "total_time": "0",
      "count": "0"
    }
  }
]